{
  "model_name": "k_nearest_neighbors",
  "optimization_type": "nested_cross_validation",
  "configuration": {
    "outer_cv_folds": 5,
    "n_trials_per_fold": 30,
    "data_source": "ANA",
    "classification_type": "multiclass",
    "timestamp": "2025-11-10T04:01:36.540713"
  },
  "aggregated_metrics": {
    "accuracy": {
      "mean": 0.6688695652173913,
      "std": 0.002825752488569021,
      "scores": [
        0.6678260869565218,
        0.671304347826087,
        0.6660869565217391,
        0.6730434782608695,
        0.6660869565217391
      ]
    },
    "precision": {
      "mean": 0.5469333798885992,
      "std": 0.02386865235400398,
      "scores": [
        0.5667234771193335,
        0.5833157146916738,
        0.5287555042537728,
        0.5343005447630794,
        0.5215716586151369
      ]
    },
    "recall": {
      "mean": 0.6688695652173913,
      "std": 0.002825752488569021,
      "scores": [
        0.6678260869565218,
        0.671304347826087,
        0.6660869565217391,
        0.6730434782608695,
        0.6660869565217391
      ]
    },
    "f1": {
      "mean": 0.5520880172570586,
      "std": 0.006519579013178984,
      "scores": [
        0.5603894936222032,
        0.5572001017402608,
        0.5470375939849623,
        0.553244932554045,
        0.5425679643838213
      ]
    },
    "roc_auc": {
      "mean": 0.5520585749457986,
      "std": 0.03188775685563062,
      "scores": [
        0.5299705779175852,
        0.5511560104732882,
        0.5842958649841075,
        0.5893485563304833,
        0.5055218650235286
      ]
    }
  },
  "best_params_per_fold": [
    {
      "n_neighbors": 16,
      "weights": "distance",
      "algorithm": "auto",
      "p": 2
    },
    {
      "n_neighbors": 20,
      "weights": "distance",
      "algorithm": "kd_tree",
      "p": 2
    },
    {
      "n_neighbors": 17,
      "weights": "distance",
      "algorithm": "brute",
      "p": 1
    },
    {
      "n_neighbors": 16,
      "weights": "distance",
      "algorithm": "kd_tree",
      "p": 2
    },
    {
      "n_neighbors": 20,
      "weights": "distance",
      "algorithm": "kd_tree",
      "p": 2
    }
  ],
  "nested_cv_summary": {
    "mean_accuracy": 0.6688695652173913,
    "std_accuracy": 0.002825752488569021,
    "mean_f1": 0.5520880172570586,
    "std_f1": 0.006519579013178984,
    "mean_roc_auc": 0.5520585749457986,
    "std_roc_auc": 0.03188775685563062
  }
}